openapi_schemas_pydantic/__init__.py
openapi_schemas_pydantic/py.typed
openapi_schemas_pydantic/utils/__init__.py
openapi_schemas_pydantic/utils/constants.py
openapi_schemas_pydantic/utils/enums.py
openapi_schemas_pydantic/utils/utils.py
openapi_schemas_pydantic/v3_1_0/__init__.py
openapi_schemas_pydantic/v3_1_0/callback.py
openapi_schemas_pydantic/v3_1_0/components.py
openapi_schemas_pydantic/v3_1_0/contact.py
openapi_schemas_pydantic/v3_1_0/discriminator.py
openapi_schemas_pydantic/v3_1_0/encoding.py
openapi_schemas_pydantic/v3_1_0/example.py
openapi_schemas_pydantic/v3_1_0/external_documentation.py
openapi_schemas_pydantic/v3_1_0/header.py
openapi_schemas_pydantic/v3_1_0/info.py
openapi_schemas_pydantic/v3_1_0/license.py
openapi_schemas_pydantic/v3_1_0/link.py
openapi_schemas_pydantic/v3_1_0/media_type.py
openapi_schemas_pydantic/v3_1_0/oauth_flow.py
openapi_schemas_pydantic/v3_1_0/oauth_flows.py
openapi_schemas_pydantic/v3_1_0/open_api.py
openapi_schemas_pydantic/v3_1_0/operation.py
openapi_schemas_pydantic/v3_1_0/parameter.py
openapi_schemas_pydantic/v3_1_0/path_item.py
openapi_schemas_pydantic/v3_1_0/paths.py
openapi_schemas_pydantic/v3_1_0/reference.py
openapi_schemas_pydantic/v3_1_0/request_body.py
openapi_schemas_pydantic/v3_1_0/response.py
openapi_schemas_pydantic/v3_1_0/responses.py
openapi_schemas_pydantic/v3_1_0/schema.py
openapi_schemas_pydantic/v3_1_0/security_requirement.py
openapi_schemas_pydantic/v3_1_0/security_scheme.py
openapi_schemas_pydantic/v3_1_0/server.py
openapi_schemas_pydantic/v3_1_0/server_variable.py
openapi_schemas_pydantic/v3_1_0/tag.py
openapi_schemas_pydantic/v3_1_0/xml.py
openapi_schemas_pydantic-3.0.0.dist-info/METADATA
openapi_schemas_pydantic-3.0.0.dist-info/WHEEL
openapi_schemas_pydantic-3.0.0.dist-info/licenses/LICENSE
openapi_schemas_pydantic-3.0.0.dist-info/RECORD
