Metadata-Version: 2.1
Name: openapi-schemas-pydantic
Version: 3.0.0
Summary: OpenAPI Schema using pydantic. Forked for Esmerald.
Project-URL: Homepage, https://github.com/dymmond/openapi-schemas-pydantic
Project-URL: Documentation, https://openapi-schemas.dymmond.com/
Project-URL: Changelog, https://openapi-schemas.dymmond.com/release-notes/
Project-URL: Funding, https://github.com/sponsors/tarsil
Project-URL: Source, https://github.com/dymmond/openapi-schemas-pydantic
Author-email: Tiago Silva <tiago.silva@dymmond.com>
License-Expression: MIT
License-File: LICENSE
Keywords: OpenAPI,open-api,openapi_schemas_pydantic,pydantic,schema
Classifier: Development Status :: 5 - Production/Stable
Classifier: Environment :: Web Environment
Classifier: License :: OSI Approved :: MIT License
Classifier: Natural Language :: English
Classifier: Operating System :: OS Independent
Classifier: Programming Language :: Python
Classifier: Programming Language :: Python :: 3.7
Classifier: Programming Language :: Python :: 3.8
Classifier: Programming Language :: Python :: 3.9
Classifier: Programming Language :: Python :: 3.10
Classifier: Topic :: Internet :: WWW/HTTP
Classifier: Topic :: Software Development
Classifier: Topic :: Software Development :: Libraries
Classifier: Typing :: Typed
Requires-Python: >=3.8
Requires-Dist: email-validator<3.0.0,>=2.0.0
Requires-Dist: pydantic-extra-types<3.0.0,>=2.0.0
Requires-Dist: pydantic<3.0.0,>=2.0.0
Provides-Extra: dev
Requires-Dist: black<30.0.0,>=23.0.0; extra == 'dev'
Requires-Dist: isort<6.0.0,>=5.12.0; extra == 'dev'
Requires-Dist: mypy==1.4.1; extra == 'dev'
Requires-Dist: pre-commit<3.0.0,>=2.17.0; extra == 'dev'
Requires-Dist: ruff<1.0.0,>=0.0.275; extra == 'dev'
Provides-Extra: doc
Requires-Dist: mdx-include<2.0.0,>=1.4.1; extra == 'doc'
Requires-Dist: mkautodoc<0.3.0,>=0.2.0; extra == 'doc'
Requires-Dist: mkdocs-markdownextradata-plugin<0.3.0,>=0.1.7; extra == 'doc'
Requires-Dist: mkdocs-material<9.0.0,>=8.1.4; extra == 'doc'
Requires-Dist: mkdocs<2.0.0,>=1.1.2; extra == 'doc'
Requires-Dist: mkdocstrings<0.23.0,>=0.19.0; extra == 'doc'
Requires-Dist: pyyaml<7.0.0,>=5.3.1; extra == 'doc'
Provides-Extra: test
Requires-Dist: pytest-asyncio<0.20.0,>=0.19.0; extra == 'test'
Requires-Dist: pytest-cov<4.0.0,>=2.12.0; extra == 'test'
Requires-Dist: pytest<8.0.0,>=7.1.3; extra == 'test'
